{"adapters_leveldb_index.md":"8e683d69","adapters_memory_index.md":"e74a4130","adapters_localstorage_index.md":"704deabf","adapters_neo4j_index.md":"40e76034","adapters_rdf_index.md":"723240fe","guide_adapters.md":"a5fd1669","guide_browser.md":"ebf7412e","adapters_sql_index.md":"083ce77b","index.md":"b51c36df","plugins_schema_index.md":"58933532","plugins_semantic_index.md":"2c35a8ce","guide_index.md":"f41cc4cb","guide_graphs.md":"e75fabac","guide_utils.md":"d2435363","guide_plugins.md":"0672f67e","guide_getting-started.md":"d290a83c"}
